PythonProjectBootstrapper/EntryPoint.py
PythonProjectBootstrapper/ProjectGenerationUtils.py
PythonProjectBootstrapper/__init__.py
PythonProjectBootstrapper/package/cookiecutter.json
PythonProjectBootstrapper/package/cookiecutter_prompts.yaml
PythonProjectBootstrapper/package/local_extensions.py
PythonProjectBootstrapper/package/hooks/post_gen_project.py
PythonProjectBootstrapper/package/hooks/pre_gen_project.py
PythonProjectBootstrapper/package/hooks/startup.py
PythonProjectBootstrapper/package/templates/python_header.py
PythonProjectBootstrapper/package/{{ cookiecutter.__empty_dir }}/ActivateEpilog.py
PythonProjectBootstrapper/package/{{ cookiecutter.__empty_dir }}/Bootstrap.cmd
PythonProjectBootstrapper/package/{{ cookiecutter.__empty_dir }}/Bootstrap.sh
PythonProjectBootstrapper/package/{{ cookiecutter.__empty_dir }}/BootstrapEpilog.py
PythonProjectBootstrapper/package/{{ cookiecutter.__empty_dir }}/Build.py
PythonProjectBootstrapper/package/{{ cookiecutter.__empty_dir }}/CODE_OF_CONDUCT.md
PythonProjectBootstrapper/package/{{ cookiecutter.__empty_dir }}/CONTRIBUTING.md
PythonProjectBootstrapper/package/{{ cookiecutter.__empty_dir }}/DEVELOPMENT.md
PythonProjectBootstrapper/package/{{ cookiecutter.__empty_dir }}/GOVERNANCE.md
PythonProjectBootstrapper/package/{{ cookiecutter.__empty_dir }}/MAINTAINERS.md
PythonProjectBootstrapper/package/{{ cookiecutter.__empty_dir }}/README.md
PythonProjectBootstrapper/package/{{ cookiecutter.__empty_dir }}/SECURITY.md
PythonProjectBootstrapper/package/{{ cookiecutter.__empty_dir }}/pyproject.toml
PythonProjectBootstrapper/package/{{ cookiecutter.__empty_dir }}/Licenses/Apache-2.0_LICENSE.txt
PythonProjectBootstrapper/package/{{ cookiecutter.__empty_dir }}/Licenses/BSD-3-Clause-Clear_LICENSE.txt
PythonProjectBootstrapper/package/{{ cookiecutter.__empty_dir }}/Licenses/BSL-1.0_LICENSE_1_0.txt
PythonProjectBootstrapper/package/{{ cookiecutter.__empty_dir }}/Licenses/GPL-3.0-or-later_LICENSE.txt
PythonProjectBootstrapper-0.3.13.dist-info/LICENSE.txt
PythonProjectBootstrapper-0.3.13.dist-info/METADATA
PythonProjectBootstrapper-0.3.13.dist-info/WHEEL
PythonProjectBootstrapper-0.3.13.dist-info/entry_points.txt
PythonProjectBootstrapper-0.3.13.dist-info/top_level.txt
PythonProjectBootstrapper-0.3.13.dist-info/RECORD
