Metadata-Version: 2.1
Name: PythonProjectBootstrapper
Version: 0.3.13
Summary: Tool that helps in the creation of python projects.
Author-email: Scientific Software Engineering Center at Georgia Tech <sse-center@gatech.edu>
License: MIT
Project-URL: Homepage, https://github.com/gt-sse-center/PythonProjectBootstrapper
Project-URL: Documentation, https://github.com/gt-sse-center/PythonProjectBootstrapper
Project-URL: Repository, https://github.com/gt-sse-center/PythonProjectBootstrapper
Classifier: License :: OSI Approved :: MIT License
Classifier: Operating System :: MacOS
Classifier: Operating System :: Microsoft :: Windows
Classifier: Operating System :: POSIX :: Linux
Classifier: Programming Language :: Python
Classifier: Programming Language :: Python :: 3.10
Classifier: Programming Language :: Python :: 3.11
Classifier: Programming Language :: Python :: 3.12
License-File: LICENSE.txt
Requires-Dist: cookiecutter ~=2.6
Requires-Dist: dbrownell-Common
Requires-Dist: rich ~=13.7
Requires-Dist: typer ~=0.9
Provides-Extra: dev
Requires-Dist: dbrownell-DevTools ; extra == 'dev'
Requires-Dist: pyfakefs ~=5.5 ; extra == 'dev'
Provides-Extra: package
Requires-Dist: build ~=1.2 ; extra == 'package'
Requires-Dist: cx-Freeze ~=6.15 ; extra == 'package'
Requires-Dist: twine ~=4.0 ; extra == 'package'
